{
	"groups":[
		{
			"keys":"bg,title_png,img_rank_bg_png",
			"name":"preload"
		},
		{
			"keys":"4hit_mp3,5hit_mp3,6hit_mp3,bg_mp3,btn_wav,hura_wav,1hit_mp3,2hit_mp3,3hit_mp3,nice_mp3,niubility_mp3,statistic_mp3,amazing_mp3,great1_mp3",
			"name":"sounds"
		},
		{
			"keys":"bg_bottom_01,bg_bottom_02,white_fnt_fnt,gold_fnt_fnt,sp,particle_json,guide_json",
			"name":"next"
		}
	],
	"resources":[
		{
			"name":"sp",
			"subkeys":"amazing,blood_01,blood_02,btn_01_down,btn_01_normal,btn_pause,btn_start_bottom,great,img_split,img_star,info_bg,lab_cancel,lab_confirm,lab_friend,lab_home,lab_refresh,new_record,nici,niubility,particle_1,particle_2,particle_3,particle_4,particle_5,particle_6,particle_8,start_btn,unit_1,unit_10,unit_11,unit_12,unit_13,unit_14,unit_15,unit_16,unit_17,unit_18,unit_19,unit_2,unit_20,unit_3,unit_4,unit_5,unit_6,unit_7,unit_8,unit_9",
			"type":"sheet",
			"url":"assets/sp.json"
		},
		{
			"name":"particle_json",
			"type":"json",
			"url":"assets/particle.json"
		},
		{
			"name":"bg",
			"type":"image",
			"url":"assets/bg.jpg"
		},
		{
			"name":"bg_bottom_01",
			"type":"image",
			"url":"assets/bg_bottom_01.png"
		},
		{
			"name":"bg_bottom_02",
			"type":"image",
			"url":"assets/bg_bottom_02.png"
		},
		{
			"name":"white_fnt_fnt",
			"type":"font",
			"url":"assets/white_fnt.fnt"
		},
		{
			"name":"gold_fnt_fnt",
			"type":"font",
			"url":"assets/gold_fnt.fnt"
		},
		{
			"name":"guide_json",
			"subkeys":"guide1,guide10,guide11,guide12,guide13,guide14,guide2,guide3,guide4,guide5,guide6,guide7,guide8,guide9,guide_txt",
			"type":"sheet",
			"url":"assets/guide.json"
		},
		{
			"name":"title_png",
			"type":"image",
			"url":"assets/title.png"
		},
		{
			"name":"img_rank_bg_png",
			"type":"image",
			"url":"assets/img_rank_bg.png"
		},
		{
			"name":"4hit_mp3",
			"type":"sound",
			"url":"assets/sound/4hit.mp3"
		},
		{
			"name":"5hit_mp3",
			"type":"sound",
			"url":"assets/sound/5hit.mp3"
		},
		{
			"name":"6hit_mp3",
			"type":"sound",
			"url":"assets/sound/6hit.mp3"
		},
		{
			"name":"bg_mp3",
			"type":"sound",
			"url":"assets/sound/bg.mp3"
		},
		{
			"name":"btn_wav",
			"type":"sound",
			"url":"assets/sound/btn.wav"
		},
		{
			"name":"hura_wav",
			"type":"sound",
			"url":"assets/sound/hura.wav"
		},
		{
			"name":"1hit_mp3",
			"type":"sound",
			"url":"assets/sound/1hit.mp3"
		},
		{
			"name":"2hit_mp3",
			"type":"sound",
			"url":"assets/sound/2hit.mp3"
		},
		{
			"name":"3hit_mp3",
			"type":"sound",
			"url":"assets/sound/3hit.mp3"
		},
		{
			"name":"nice_mp3",
			"type":"sound",
			"url":"assets/sound/nice.mp3"
		},
		{
			"name":"niubility_mp3",
			"type":"sound",
			"url":"assets/sound/niubility.mp3"
		},
		{
			"name":"statistic_mp3",
			"type":"sound",
			"url":"assets/sound/statistic.mp3"
		},
		{
			"name":"amazing_mp3",
			"type":"sound",
			"url":"assets/sound/amazing.mp3"
		},
		{
			"name":"great1_mp3",
			"type":"sound",
			"url":"assets/sound/great1.mp3"
		}
	]
}